{
  "deals": [
    {
      "id": "Titan Cards::pokemon tcg mega evolution chaos rising elite trainer box",
      "product": "Pokemon TCG Mega Evolution Chaos Rising Elite Trainer Box",
      "retailer": "Titan Cards",
      "buyNow": 64.99,
      "rrp": 49.99,
      "resell": 69.02,
      "dealScore": 44,
      "grade": "C",
      "resellSource": "ebay_browse",
      "resellConfidence": "HIGH",
      "resellSampleSize": 13,
      "resellFreshness": "2026-07-18T15:09:27.556Z",
      "url": "https://titancards.co.uk/products/pokemon-tcg-mega-evolution-chaos-rising-elite-trainer-box",
      "image": "https://cdn.shopify.com/s/files/1/0795/2397/1402/files/Chaos-Rising-ETB1.webp?v=1784027904",
      "lastSeen": "2026-07-18T15:09:27.806Z",
      "isPriceDrop": false,
      "oldPrice": null
    },
    {
      "id": "Titan Cards::pokemon tcg mega evolution pitch black booster pack",
      "product": "Pokemon TCG Mega Evolution Pitch Black Booster Pack",
      "retailer": "Titan Cards",
      "buyNow": 6.75,
      "rrp": 4.99,
      "resell": 6.37,
      "dealScore": 25,
      "grade": "D",
      "resellSource": "ebay_browse",
      "resellConfidence": "HIGH",
      "resellSampleSize": 9,
      "resellFreshness": "2026-07-18T15:09:28.489Z",
      "url": "https://titancards.co.uk/products/pokemon-tcg-mega-evolution-pitch-black-booster-pack",
      "image": "https://cdn.shopify.com/s/files/1/0795/2397/1402/files/Pokemon-Pitch-Black-Booster-Pack_b4beba1d-34c3-4798-9ac0-4262b8cfc2c5.jpg?v=1783790008",
      "lastSeen": "2026-07-18T15:09:28.739Z",
      "isPriceDrop": false,
      "oldPrice": null
    },
    {
      "id": "Titan Cards::pokémon tcg: team rocket's mewtwo ex league battle deck",
      "product": "Pokémon TCG: Team Rocket's Mewtwo EX League Battle Deck",
      "retailer": "Titan Cards",
      "buyNow": 37.95,
      "rrp": 34.99,
      "resell": 45.24,
      "dealScore": 60,
      "grade": "B",
      "resellSource": "ebay_browse",
      "resellConfidence": "MEDIUM",
      "resellSampleSize": 5,
      "resellFreshness": "2026-07-18T15:09:29.357Z",
      "url": "https://titancards.co.uk/products/pokemon-tcg-team-rockets-mewtwo-ex-league-battle-deck",
      "image": "https://cdn.shopify.com/s/files/1/0795/2397/1402/files/Team-Rockets-Mewtwo-EX-Deck.webp?v=1782308244",
      "lastSeen": "2026-07-18T15:09:29.608Z",
      "isPriceDrop": false,
      "oldPrice": null
    },
    {
      "id": "Titan Cards::mega evolution chaos rising booster pack | pokémon tcg mega evolution pack",
      "product": "Mega Evolution Chaos Rising Booster Pack | Pokémon TCG Mega Evolution Pack",
      "retailer": "Titan Cards",
      "buyNow": 6.75,
      "rrp": 4.99,
      "resell": 7.23,
      "dealScore": 25,
      "grade": "D",
      "resellSource": "ebay_browse",
      "resellConfidence": "HIGH",
      "resellSampleSize": 8,
      "resellFreshness": "2026-07-18T15:09:30.213Z",
      "url": "https://titancards.co.uk/products/pokemon-tcg-chaos-rising-booster-pack",
      "image": "https://cdn.shopify.com/s/files/1/0795/2397/1402/files/Chaos-Rising-Booster-Pack.webp?v=1779885528",
      "lastSeen": "2026-07-18T15:09:30.464Z",
      "isPriceDrop": false,
      "oldPrice": null
    },
    {
      "id": "Titan Cards::pokemon tcg nihil zero m3 booster box | 30x nihil zero booster packs | korean version of perfect order",
      "product": "Pokemon TCG Nihil Zero M3 Booster Box | 30x Nihil Zero Booster Packs | Korean version of Perfect Order",
      "retailer": "Titan Cards",
      "buyNow": 49.99,
      "rrp": 134.99,
      "resell": 60,
      "dealScore": 30,
      "grade": "H",
      "resellSource": "static_table",
      "resellConfidence": null,
      "resellSampleSize": null,
      "resellFreshness": null,
      "url": "https://titancards.co.uk/products/pokemon-nihil-zero-m3-booster-box-korean-perfect-order",
      "image": "https://cdn.shopify.com/s/files/1/0795/2397/1402/files/Nihil-Zero-Korean-Booster-Box.jpg?v=1774613150",
      "lastSeen": "2026-07-18T15:09:31.259Z",
      "isPriceDrop": false,
      "oldPrice": null
    },
    {
      "id": "Titan Cards::mega evolution perfect order booster pack | pokémon tcg mega evolution pack",
      "product": "Mega Evolution Perfect Order Booster Pack | Pokémon TCG Mega Evolution Pack",
      "retailer": "Titan Cards",
      "buyNow": 6.75,
      "rrp": 4.99,
      "resell": 6.8,
      "dealScore": 29,
      "grade": "H",
      "resellSource": "ebay_browse",
      "resellConfidence": "MEDIUM",
      "resellSampleSize": 7,
      "resellFreshness": "2026-07-18T15:09:31.850Z",
      "url": "https://titancards.co.uk/products/mega-evolution-perfect-order-booster-pack",
      "image": "https://cdn.shopify.com/s/files/1/0795/2397/1402/files/Perfect-Order-Booster-Pack-1.jpg?v=1774438317",
      "lastSeen": "2026-07-18T15:09:32.101Z",
      "isPriceDrop": false,
      "oldPrice": null
    },
    {
      "id": "Eterna Cards::pokemon chaos rising booster pack bundle (9 packs)",
      "product": "Pokemon Chaos Rising Booster Pack Bundle (9 Packs)",
      "retailer": "Eterna Cards",
      "buyNow": 53.89,
      "rrp": 4.99,
      "resell": 6.24,
      "dealScore": 20,
      "grade": "D",
      "resellSource": "ebay_browse",
      "resellConfidence": "MEDIUM",
      "resellSampleSize": 7,
      "resellFreshness": "2026-07-18T15:09:32.686Z",
      "url": "https://eternacards.co.uk/products/pokemon-chaos-rising-booster-pack-bundle-9-packs-1",
      "image": "https://cdn.shopify.com/s/files/1/0586/9243/5991/files/pokemon-chaos-rising-booster-pack-bundle-9-packs-1531029.png?v=1779919167",
      "lastSeen": "2026-07-18T15:09:32.937Z",
      "isPriceDrop": false,
      "oldPrice": null
    },
    {
      "id": "Eterna Cards::pokemon chaos rising booster pack",
      "product": "Pokemon Chaos Rising Booster Pack",
      "retailer": "Eterna Cards",
      "buyNow": 5.99,
      "rrp": 4.99,
      "resell": 6.11,
      "dealScore": 25,
      "grade": "D",
      "resellSource": "ebay_browse",
      "resellConfidence": "HIGH",
      "resellSampleSize": 8,
      "resellFreshness": "2026-07-18T15:09:33.522Z",
      "url": "https://eternacards.co.uk/products/pokemon-chaos-rising-booster-pack-1",
      "image": "https://cdn.shopify.com/s/files/1/0586/9243/5991/files/pokemon-chaos-rising-booster-pack-6788672.png?v=1776114411",
      "lastSeen": "2026-07-18T15:09:33.772Z",
      "isPriceDrop": false,
      "oldPrice": null
    },
    {
      "id": "Eterna Cards::pokemon prismatic evolutions elite trainer box",
      "product": "Pokemon Prismatic Evolutions Elite Trainer Box",
      "retailer": "Eterna Cards",
      "buyNow": 154.95,
      "rrp": 49.99,
      "resell": 148.35,
      "dealScore": 39,
      "grade": "H",
      "resellSource": "ebay_browse",
      "resellConfidence": "HIGH",
      "resellSampleSize": 11,
      "resellFreshness": "2026-07-18T15:09:34.341Z",
      "url": "https://eternacards.co.uk/products/pokemon-prismatic-evolutions-elite-trainer-box",
      "image": "https://cdn.shopify.com/s/files/1/0586/9243/5991/files/pokemon-prismatic-evolutions-elite-trainer-box-9971688.png?v=1782186792",
      "lastSeen": "2026-07-18T15:09:34.591Z",
      "isPriceDrop": false,
      "oldPrice": null
    },
    {
      "id": "Eterna Cards::pokemon fossil set blister booster pack (unweighed) (lapras artwork)﹒",
      "product": "Pokemon Fossil Set Blister Booster Pack (Unweighed) (Lapras Artwork)﹒",
      "retailer": "Eterna Cards",
      "buyNow": 469.95,
      "rrp": 4.99,
      "resell": null,
      "dealScore": 30,
      "grade": "D",
      "resellSource": null,
      "resellConfidence": null,
      "resellSampleSize": null,
      "resellFreshness": null,
      "url": "https://eternacards.co.uk/products/fossil-set-blister-booster-pack-unweighed-lapras-artwork",
      "image": "https://cdn.shopify.com/s/files/1/0586/9243/5991/files/pokemon-fossil-set-blister-booster-pack-unweighed-lapras-artwork-7926699.png?v=1781633425",
      "lastSeen": "2026-07-18T15:09:35.356Z",
      "isPriceDrop": false,
      "oldPrice": null
    },
    {
      "id": "Eterna Cards::pokemon prismatic evolutions mini tin display case (sealed)﹒",
      "product": "Pokemon Prismatic Evolutions Mini Tin Display Case (Sealed)﹒",
      "retailer": "Eterna Cards",
      "buyNow": 279.95,
      "rrp": 14.99,
      "resell": null,
      "dealScore": 30,
      "grade": "H",
      "resellSource": null,
      "resellConfidence": null,
      "resellSampleSize": null,
      "resellFreshness": null,
      "url": "https://eternacards.co.uk/products/prismatic-evolutions-mini-tin-display-case",
      "image": "https://cdn.shopify.com/s/files/1/0586/9243/5991/files/pokemon-prismatic-evolutions-mini-tin-display-case-sealed-1852778.png?v=1781633421",
      "lastSeen": "2026-07-18T15:09:36.244Z",
      "isPriceDrop": false,
      "oldPrice": null
    },
    {
      "id": "Eterna Cards::pokemon 151 mini tin display case (sealed)﹒",
      "product": "Pokemon 151 Mini Tin Display Case (Sealed)﹒",
      "retailer": "Eterna Cards",
      "buyNow": 529.95,
      "rrp": 14.99,
      "resell": 26.69,
      "dealScore": 26,
      "grade": "D",
      "resellSource": "ebay_browse",
      "resellConfidence": "LOW",
      "resellSampleSize": 1,
      "resellFreshness": "2026-07-18T15:09:36.782Z",
      "url": "https://eternacards.co.uk/products/151-mini-tin-display-case",
      "image": "https://cdn.shopify.com/s/files/1/0586/9243/5991/files/pokemon-151-mini-tin-display-case-sealed-8694166.png?v=1781633424",
      "lastSeen": "2026-07-18T15:09:37.033Z",
      "isPriceDrop": false,
      "oldPrice": null
    },
    {
      "id": "Eterna Cards::pokemon 151 elite trainer box (sealed)﹒",
      "product": "Pokemon 151 Elite Trainer Box (Sealed)﹒",
      "retailer": "Eterna Cards",
      "buyNow": 479.95,
      "rrp": 49.99,
      "resell": 65,
      "dealScore": 30,
      "grade": "H",
      "resellSource": "static_table",
      "resellConfidence": null,
      "resellSampleSize": null,
      "resellFreshness": null,
      "url": "https://eternacards.co.uk/products/151-elite-trainer-box",
      "image": "https://cdn.shopify.com/s/files/1/0586/9243/5991/files/pokemon-151-elite-trainer-box-sealed-9897232.png?v=1781633427",
      "lastSeen": "2026-07-18T15:09:37.754Z",
      "isPriceDrop": false,
      "oldPrice": null
    },
    {
      "id": "Eterna Cards::pokemon jungle set short crimp booster pack (unweighed) (scyther artwork)﹒",
      "product": "Pokemon Jungle Set Short Crimp Booster Pack (Unweighed) (Scyther Artwork)﹒",
      "retailer": "Eterna Cards",
      "buyNow": 289.95,
      "rrp": 4.99,
      "resell": null,
      "dealScore": 30,
      "grade": "D",
      "resellSource": null,
      "resellConfidence": null,
      "resellSampleSize": null,
      "resellFreshness": null,
      "url": "https://eternacards.co.uk/products/jungle-set-short-crimp-booster-pack-unweighed-scyther-artwork",
      "image": "https://cdn.shopify.com/s/files/1/0586/9243/5991/files/pokemon-jungle-set-short-crimp-booster-pack-unweighed-scyther-artwork-6713828.png?v=1781449571",
      "lastSeen": "2026-07-18T15:09:38.441Z",
      "isPriceDrop": false,
      "oldPrice": null
    },
    {
      "id": "Eterna Cards::pokemon jungle set short crimp booster pack (unweighed) (flareon artwork)﹒",
      "product": "Pokemon Jungle Set Short Crimp Booster Pack (Unweighed) (Flareon Artwork)﹒",
      "retailer": "Eterna Cards",
      "buyNow": 309.95,
      "rrp": 4.99,
      "resell": null,
      "dealScore": 30,
      "grade": "D",
      "resellSource": null,
      "resellConfidence": null,
      "resellSampleSize": null,
      "resellFreshness": null,
      "url": "https://eternacards.co.uk/products/jungle-set-short-crimp-booster-pack-unweighed-flareon-artwork",
      "image": "https://cdn.shopify.com/s/files/1/0586/9243/5991/files/pokemon-jungle-set-short-crimp-booster-pack-unweighed-flareon-artwork-2392727.png?v=1781449572",
      "lastSeen": "2026-07-18T15:09:39.261Z",
      "isPriceDrop": false,
      "oldPrice": null
    },
    {
      "id": "Eterna Cards::pokemon jungle set short crimp booster pack (unweighed) (wigglytuff artwork)﹒",
      "product": "Pokemon Jungle Set Short Crimp Booster Pack (Unweighed) (Wigglytuff Artwork)﹒",
      "retailer": "Eterna Cards",
      "buyNow": 309.95,
      "rrp": 4.99,
      "resell": null,
      "dealScore": 30,
      "grade": "D",
      "resellSource": null,
      "resellConfidence": null,
      "resellSampleSize": null,
      "resellFreshness": null,
      "url": "https://eternacards.co.uk/products/jungle-set-short-crimp-booster-pack-unweighed-wigglytuff-artwork",
      "image": "https://cdn.shopify.com/s/files/1/0586/9243/5991/files/pokemon-jungle-set-short-crimp-booster-pack-unweighed-wigglytuff-artwork-3198086.png?v=1781449572",
      "lastSeen": "2026-07-18T15:09:40.019Z",
      "isPriceDrop": false,
      "oldPrice": null
    },
    {
      "id": "Eterna Cards::pokemon base set 2 long crimp booster pack (unweighed) (pidgeot artwork)﹒",
      "product": "Pokemon Base Set 2 Long Crimp Booster Pack (Unweighed) (Pidgeot Artwork)﹒",
      "retailer": "Eterna Cards",
      "buyNow": 309.95,
      "rrp": 4.99,
      "resell": null,
      "dealScore": 30,
      "grade": "D",
      "resellSource": null,
      "resellConfidence": null,
      "resellSampleSize": null,
      "resellFreshness": null,
      "url": "https://eternacards.co.uk/products/base-set-2-long-crimp-booster-pack-unweighed-pidgeot-artwork",
      "image": "https://cdn.shopify.com/s/files/1/0586/9243/5991/files/pokemon-base-set-2-long-crimp-booster-pack-unweighed-pidgeot-artwork-8904558.png?v=1781449573",
      "lastSeen": "2026-07-18T15:09:40.818Z",
      "isPriceDrop": false,
      "oldPrice": null
    },
    {
      "id": "Eterna Cards::pokemon base set 2 long crimp booster pack (unweighed) (raichu artwork)﹒",
      "product": "Pokemon Base Set 2 Long Crimp Booster Pack (Unweighed) (Raichu Artwork)﹒",
      "retailer": "Eterna Cards",
      "buyNow": 319.95,
      "rrp": 4.99,
      "resell": null,
      "dealScore": 30,
      "grade": "D",
      "resellSource": null,
      "resellConfidence": null,
      "resellSampleSize": null,
      "resellFreshness": null,
      "url": "https://eternacards.co.uk/products/base-set-2-long-crimp-booster-pack-unweighed-raichu-artwork",
      "image": "https://cdn.shopify.com/s/files/1/0586/9243/5991/files/pokemon-base-set-2-long-crimp-booster-pack-unweighed-raichu-artwork-5506101.png?v=1781449572",
      "lastSeen": "2026-07-18T15:09:41.709Z",
      "isPriceDrop": false,
      "oldPrice": null
    },
    {
      "id": "Eterna Cards::pokemon base set 2 long crimp booster pack (unweighed) (mewtwo artwork)﹒",
      "product": "Pokemon Base Set 2 Long Crimp Booster Pack (Unweighed) (Mewtwo Artwork)﹒",
      "retailer": "Eterna Cards",
      "buyNow": 329.95,
      "rrp": 4.99,
      "resell": null,
      "dealScore": 30,
      "grade": "D",
      "resellSource": null,
      "resellConfidence": null,
      "resellSampleSize": null,
      "resellFreshness": null,
      "url": "https://eternacards.co.uk/products/base-set-2-long-crimp-booster-pack-unweighed-mewtwo-artwork",
      "image": "https://cdn.shopify.com/s/files/1/0586/9243/5991/files/pokemon-base-set-2-long-crimp-booster-pack-unweighed-mewtwo-artwork-2276065.png?v=1781449572",
      "lastSeen": "2026-07-18T15:09:42.466Z",
      "isPriceDrop": false,
      "oldPrice": null
    },
    {
      "id": "Eterna Cards::pokemon base set 2 long crimp booster pack (unweighed) (gyarados artwork)﹒",
      "product": "Pokemon Base Set 2 Long Crimp Booster Pack (Unweighed) (Gyarados Artwork)﹒",
      "retailer": "Eterna Cards",
      "buyNow": 339.95,
      "rrp": 4.99,
      "resell": null,
      "dealScore": 30,
      "grade": "D",
      "resellSource": null,
      "resellConfidence": null,
      "resellSampleSize": null,
      "resellFreshness": null,
      "url": "https://eternacards.co.uk/products/base-set-2-long-crimp-booster-pack-unweighed-gyarados-artwork",
      "image": "https://cdn.shopify.com/s/files/1/0586/9243/5991/files/pokemon-base-set-2-long-crimp-booster-pack-unweighed-gyarados-artwork-5066861.png?v=1781449573",
      "lastSeen": "2026-07-18T15:09:43.160Z",
      "isPriceDrop": false,
      "oldPrice": null
    },
    {
      "id": "Eterna Cards::pokemon base set long crimp booster pack (unweighed) (blastoise artwork)﹒",
      "product": "Pokemon Base Set Long Crimp Booster Pack (Unweighed) (Blastoise Artwork)﹒",
      "retailer": "Eterna Cards",
      "buyNow": 469.95,
      "rrp": 4.99,
      "resell": null,
      "dealScore": 30,
      "grade": "D",
      "resellSource": null,
      "resellConfidence": null,
      "resellSampleSize": null,
      "resellFreshness": null,
      "url": "https://eternacards.co.uk/products/base-set-long-crimp-booster-pack-unweighed-blastoise-artwork",
      "image": "https://cdn.shopify.com/s/files/1/0586/9243/5991/files/pokemon-base-set-long-crimp-booster-pack-unweighed-blastoise-artwork-1919582.png?v=1781264252",
      "lastSeen": "2026-07-18T15:09:44.046Z",
      "isPriceDrop": false,
      "oldPrice": null
    },
    {
      "id": "Eterna Cards::pokemon base set long crimp booster pack (unweighed) (venusaur artwork)﹒",
      "product": "Pokemon Base Set Long Crimp Booster Pack (Unweighed) (Venusaur Artwork)﹒",
      "retailer": "Eterna Cards",
      "buyNow": 489.95,
      "rrp": 4.99,
      "resell": null,
      "dealScore": 30,
      "grade": "D",
      "resellSource": null,
      "resellConfidence": null,
      "resellSampleSize": null,
      "resellFreshness": null,
      "url": "https://eternacards.co.uk/products/base-set-long-crimp-booster-pack-unweighed-venusaur-artwork",
      "image": "https://cdn.shopify.com/s/files/1/0586/9243/5991/files/pokemon-base-set-long-crimp-booster-pack-unweighed-venusaur-artwork-2073815.png?v=1781264252",
      "lastSeen": "2026-07-18T15:09:44.871Z",
      "isPriceDrop": false,
      "oldPrice": null
    },
    {
      "id": "Double Sleeved::pokemon tcg: team rocket's mewtwo ex league battle deck",
      "product": "Pokemon TCG: Team Rocket's Mewtwo ex League Battle Deck",
      "retailer": "Double Sleeved",
      "buyNow": 19.99,
      "rrp": 34.99,
      "resell": 45.24,
      "dealScore": 95,
      "grade": "S",
      "resellSource": "ebay_browse",
      "resellConfidence": "MEDIUM",
      "resellSampleSize": 5,
      "resellFreshness": "2026-07-18T15:09:45.400Z",
      "url": "https://www.doublesleeved.co.uk/products/pokemon-tcg-team-rockets-mewtwo-ex-league-battle-deck",
      "image": "https://cdn.shopify.com/s/files/1/0268/9217/3400/files/team-rockets-mewtwo-ex-on-white-square.png?v=1784129595",
      "lastSeen": "2026-07-18T15:09:45.651Z",
      "isPriceDrop": false,
      "oldPrice": null
    },
    {
      "id": "Double Sleeved::pokemon tcg: phantasmal flames me02 - 3-pack blister",
      "product": "Pokemon TCG: Phantasmal Flames ME02 - 3-Pack Blister",
      "retailer": "Double Sleeved",
      "buyNow": 29.99,
      "rrp": null,
      "resell": 16.63,
      "dealScore": 36,
      "grade": "H",
      "resellSource": "ebay_browse",
      "resellConfidence": "HIGH",
      "resellSampleSize": 8,
      "resellFreshness": "2026-07-18T15:09:46.572Z",
      "url": "https://www.doublesleeved.co.uk/products/pokemon-tcg-phantasmal-flames-me02-3-pack-blister",
      "image": "https://cdn.shopify.com/s/files/1/0268/9217/3400/files/P10347_10-10187-108_01.jpg?v=1783593846",
      "lastSeen": "2026-07-18T15:09:46.823Z",
      "isPriceDrop": false,
      "oldPrice": null
    },
    {
      "id": "Double Sleeved::pokemon tcg: twilight masquerade - sleeved booster pack",
      "product": "Pokemon TCG: Twilight Masquerade - Sleeved Booster Pack",
      "retailer": "Double Sleeved",
      "buyNow": 10.99,
      "rrp": 4.99,
      "resell": 12.94,
      "dealScore": 15,
      "grade": "D",
      "resellSource": "ebay_browse",
      "resellConfidence": "LOW",
      "resellSampleSize": 1,
      "resellFreshness": "2026-07-18T15:09:47.366Z",
      "url": "https://www.doublesleeved.co.uk/products/pokemon-tcg-twilight-masquerade-sleeved-booster-pack",
      "image": "https://cdn.shopify.com/s/files/1/0268/9217/3400/files/pokemon-tcg-twilight-masquerade-sleeved-booster-ursaluna.webp?v=1783007109",
      "lastSeen": "2026-07-18T15:09:47.617Z",
      "isPriceDrop": false,
      "oldPrice": null
    },
    {
      "id": "Double Sleeved::pokemon tcg: burning shadows - booster box",
      "product": "Pokemon TCG: Burning Shadows - Booster Box",
      "retailer": "Double Sleeved",
      "buyNow": 949,
      "rrp": 134.99,
      "resell": 360,
      "dealScore": 15,
      "grade": "D",
      "resellSource": "ebay_browse",
      "resellConfidence": "LOW",
      "resellSampleSize": 1,
      "resellFreshness": "2026-07-18T15:09:48.214Z",
      "url": "https://www.doublesleeved.co.uk/products/pokemon-tcg-burning-shadows-booster-box",
      "image": "https://cdn.shopify.com/s/files/1/0268/9217/3400/files/pokemon-tcg-burning-shadows-booster-box.webp?v=1782913904",
      "lastSeen": "2026-07-18T15:09:48.464Z",
      "isPriceDrop": false,
      "oldPrice": null
    },
    {
      "id": "Double Sleeved::pokemon tcg: chaos rising me04 - booster pack",
      "product": "Pokemon TCG: Chaos Rising ME04 - Booster Pack",
      "retailer": "Double Sleeved",
      "buyNow": 6.49,
      "rrp": 4.99,
      "resell": 7.91,
      "dealScore": 20,
      "grade": "D",
      "resellSource": "ebay_browse",
      "resellConfidence": "MEDIUM",
      "resellSampleSize": 6,
      "resellFreshness": "2026-07-18T15:09:49.026Z",
      "url": "https://www.doublesleeved.co.uk/products/pokemon-tcg-chaos-rising-me04-booster-pack",
      "image": "https://cdn.shopify.com/s/files/1/0268/9217/3400/files/Pokemon-TCG-Chaos-Rising-Booster-Pack.webp?v=1781701470",
      "lastSeen": "2026-07-18T15:09:49.277Z",
      "isPriceDrop": false,
      "oldPrice": null
    },
    {
      "id": "Double Sleeved::pokemon tcg: chaos rising - booster bundle case (25)",
      "product": "Pokemon TCG: Chaos Rising - Booster Bundle Case (25)",
      "retailer": "Double Sleeved",
      "buyNow": 1049,
      "rrp": 34.99,
      "resell": 37.99,
      "dealScore": 15,
      "grade": "D",
      "resellSource": "ebay_browse",
      "resellConfidence": "LOW",
      "resellSampleSize": 1,
      "resellFreshness": "2026-07-18T15:09:49.761Z",
      "url": "https://www.doublesleeved.co.uk/products/pokemon-tcg-chaos-rising-booster-bundle-case-25",
      "image": "https://cdn.shopify.com/s/files/1/0268/9217/3400/files/pokemon-tcg-chaos-rising-booster-bundle-case.webp?v=1779806243",
      "lastSeen": "2026-07-18T15:09:50.012Z",
      "isPriceDrop": false,
      "oldPrice": null
    },
    {
      "id": "Double Sleeved::pokemon tcg: chaos rising - etb case",
      "product": "Pokemon TCG: Chaos Rising - ETB Case",
      "retailer": "Double Sleeved",
      "buyNow": 799,
      "rrp": 49.99,
      "resell": 105.95,
      "dealScore": 20,
      "grade": "D",
      "resellSource": "ebay_browse",
      "resellConfidence": "MEDIUM",
      "resellSampleSize": 5,
      "resellFreshness": "2026-07-18T15:09:50.796Z",
      "url": "https://www.doublesleeved.co.uk/products/pokemon-tcg-chaos-rising-etb-case",
      "image": "https://cdn.shopify.com/s/files/1/0268/9217/3400/files/pokemon-tcg-chaos-rising-etb-case_62bc6ee1-2ff7-4387-8b78-6501c52e1510.webp?v=1781617491",
      "lastSeen": "2026-07-18T15:09:51.047Z",
      "isPriceDrop": false,
      "oldPrice": null
    },
    {
      "id": "Double Sleeved::pokemon tcg: silver tempest - booster box case",
      "product": "Pokemon TCG: Silver Tempest - Booster Box Case",
      "retailer": "Double Sleeved",
      "buyNow": 2799,
      "rrp": 134.99,
      "resell": 145,
      "dealScore": 23,
      "grade": "D",
      "resellSource": "ebay_browse",
      "resellConfidence": "LOW",
      "resellSampleSize": 2,
      "resellFreshness": "2026-07-18T15:09:51.545Z",
      "url": "https://www.doublesleeved.co.uk/products/pokemon-tcg-silver-tempest-booster-box-case",
      "image": "https://cdn.shopify.com/s/files/1/0268/9217/3400/files/pokemon-tcg-silver-tempest-booster-box-case.webp?v=1779459712",
      "lastSeen": "2026-07-18T15:09:51.796Z",
      "isPriceDrop": false,
      "oldPrice": null
    },
    {
      "id": "Double Sleeved::pokemon tcg: battle styles - booster box case",
      "product": "Pokemon TCG: Battle Styles - Booster Box Case",
      "retailer": "Double Sleeved",
      "buyNow": 1549,
      "rrp": 134.99,
      "resell": 270,
      "dealScore": 30,
      "grade": "H",
      "resellSource": "static_table",
      "resellConfidence": null,
      "resellSampleSize": null,
      "resellFreshness": null,
      "url": "https://www.doublesleeved.co.uk/products/pokemon-tcg-battle-styles-booster-box-case",
      "image": "https://cdn.shopify.com/s/files/1/0268/9217/3400/files/pokemon-tcg-battle-styles-booster-box-case.webp?v=1779459346",
      "lastSeen": "2026-07-18T15:09:52.622Z",
      "isPriceDrop": false,
      "oldPrice": null
    },
    {
      "id": "Double Sleeved::pokemon tcg: obsidian flames - booster box case",
      "product": "Pokemon TCG: Obsidian Flames - Booster Box Case",
      "retailer": "Double Sleeved",
      "buyNow": 2099,
      "rrp": 134.99,
      "resell": 210,
      "dealScore": 28,
      "grade": "H",
      "resellSource": "ebay_browse",
      "resellConfidence": "MEDIUM",
      "resellSampleSize": 3,
      "resellFreshness": "2026-07-18T15:09:53.104Z",
      "url": "https://www.doublesleeved.co.uk/products/pokemon-tcg-obsidian-flames-booster-box-case",
      "image": "https://cdn.shopify.com/s/files/1/0268/9217/3400/files/pokemon-tcg-obsidian-flames-booster-case_21149f7d-cf6b-4c99-80d8-b12ec8ab84b6.webp?v=1779460013",
      "lastSeen": "2026-07-18T15:09:53.355Z",
      "isPriceDrop": false,
      "oldPrice": null
    },
    {
      "id": "Double Sleeved::pokemon tcg: chaos rising me04 - 3-pack blister",
      "product": "Pokemon TCG: Chaos Rising ME04 - 3-Pack Blister",
      "retailer": "Double Sleeved",
      "buyNow": 20.95,
      "rrp": null,
      "resell": 19.81,
      "dealScore": 25,
      "grade": "D",
      "resellSource": "ebay_browse",
      "resellConfidence": "HIGH",
      "resellSampleSize": 10,
      "resellFreshness": "2026-07-18T15:09:54.018Z",
      "url": "https://www.doublesleeved.co.uk/products/pokemon-tcg-chaos-rising-me04-3-pack-blisters",
      "image": "https://cdn.shopify.com/s/files/1/0268/9217/3400/files/Pokemon-TCG-Chaos-Rising-3-Pack-Blister.webp?v=1779358317",
      "lastSeen": "2026-07-18T15:09:54.269Z",
      "isPriceDrop": false,
      "oldPrice": null
    },
    {
      "id": "Double Sleeved::pokemon tcg: chaos rising me04 - sleeved booster pack (random artwork)",
      "product": "Pokemon TCG: Chaos Rising ME04 - Sleeved Booster Pack (Random Artwork)",
      "retailer": "Double Sleeved",
      "buyNow": 6.49,
      "rrp": 4.99,
      "resell": 6,
      "dealScore": 30,
      "grade": "D",
      "resellSource": "static_table",
      "resellConfidence": null,
      "resellSampleSize": null,
      "resellFreshness": null,
      "url": "https://www.doublesleeved.co.uk/products/pokemon-tcg-chaos-rising-me04-sleeved-pack-random-artwork",
      "image": "https://cdn.shopify.com/s/files/1/0268/9217/3400/files/pokemon-tcg-chaos-rising-sleeved-booster-pack-greninja.webp?v=1779805268",
      "lastSeen": "2026-07-18T15:09:55.036Z",
      "isPriceDrop": false,
      "oldPrice": null
    },
    {
      "id": "Double Sleeved::pokemon tcg: unbroken bonds - booster box",
      "product": "Pokemon TCG: Unbroken Bonds - Booster Box",
      "retailer": "Double Sleeved",
      "buyNow": 2699,
      "rrp": 134.99,
      "resell": 185,
      "dealScore": 20,
      "grade": "D",
      "resellSource": "ebay_browse",
      "resellConfidence": "MEDIUM",
      "resellSampleSize": 3,
      "resellFreshness": "2026-07-18T15:09:55.608Z",
      "url": "https://www.doublesleeved.co.uk/products/pokemon-tcg-unbroken-bonds-booster-box",
      "image": "https://cdn.shopify.com/s/files/1/0268/9217/3400/files/pokemon-tcg-unbroken-bonds-booster-box.webp?v=1778769603",
      "lastSeen": "2026-07-18T15:09:55.859Z",
      "isPriceDrop": false,
      "oldPrice": null
    },
    {
      "id": "Double Sleeved::pokemon tcg: ascended heroes - mini tin case",
      "product": "Pokemon TCG: Ascended Heroes - Mini Tin Case",
      "retailer": "Double Sleeved",
      "buyNow": 1200,
      "rrp": 14.99,
      "resell": 32.42,
      "dealScore": 32,
      "grade": "H",
      "resellSource": "ebay_browse",
      "resellConfidence": "MEDIUM",
      "resellSampleSize": 3,
      "resellFreshness": "2026-07-18T15:09:56.666Z",
      "url": "https://www.doublesleeved.co.uk/products/pokemon-tcg-ascended-heroes-mini-tin-case",
      "image": "https://cdn.shopify.com/s/files/1/0268/9217/3400/files/pokemon-tcg-ascended-heroes-mini-tin-display-case.webp?v=1778683013",
      "lastSeen": "2026-07-18T15:09:56.916Z",
      "isPriceDrop": false,
      "oldPrice": null
    },
    {
      "id": "Double Sleeved::pokemon tcg: prismatic evolutions - super premium collection case (4)",
      "product": "Pokemon TCG: Prismatic Evolutions - Super Premium Collection Case (4)",
      "retailer": "Double Sleeved",
      "buyNow": 1325,
      "rrp": 39.99,
      "resell": 414.7,
      "dealScore": 29,
      "grade": "H",
      "resellSource": "ebay_browse",
      "resellConfidence": "LOW",
      "resellSampleSize": 1,
      "resellFreshness": "2026-07-18T15:09:57.428Z",
      "url": "https://www.doublesleeved.co.uk/products/pokemon-tcg-prismatic-evolutions-super-premium-collection-case-4",
      "image": "https://cdn.shopify.com/s/files/1/0268/9217/3400/files/pokemon-tcg-prismatic-evolutions-super-premium-collection-sealed-case.webp?v=1778078537",
      "lastSeen": "2026-07-18T15:09:57.679Z",
      "isPriceDrop": false,
      "oldPrice": null
    },
    {
      "id": "Double Sleeved::pokemon tcg: ascended heroes - booster bundle case (25)",
      "product": "Pokemon TCG: Ascended Heroes - Booster Bundle Case (25)",
      "retailer": "Double Sleeved",
      "buyNow": 2099,
      "rrp": 34.99,
      "resell": 82.17,
      "dealScore": 32,
      "grade": "H",
      "resellSource": "ebay_browse",
      "resellConfidence": "MEDIUM",
      "resellSampleSize": 3,
      "resellFreshness": "2026-07-18T15:09:58.370Z",
      "url": "https://www.doublesleeved.co.uk/products/pokemon-tcg-ascended-heroes-booster-bundle-case-25",
      "image": "https://cdn.shopify.com/s/files/1/0268/9217/3400/files/pokemon-tcg-ascended-heroes-booster-bundle-case.webp?v=1778078236",
      "lastSeen": "2026-07-18T15:09:58.621Z",
      "isPriceDrop": false,
      "oldPrice": null
    },
    {
      "id": "Double Sleeved::pokemon tcg: perfect order - booster bundle",
      "product": "Pokemon TCG: Perfect Order - Booster Bundle",
      "retailer": "Double Sleeved",
      "buyNow": 39.95,
      "rrp": 34.99,
      "resell": 38.14,
      "dealScore": 34,
      "grade": "H",
      "resellSource": "ebay_browse",
      "resellConfidence": "HIGH",
      "resellSampleSize": 12,
      "resellFreshness": "2026-07-18T15:09:59.257Z",
      "url": "https://www.doublesleeved.co.uk/products/pokemon-tcg-perfect-order-booster-bundle",
      "image": "https://cdn.shopify.com/s/files/1/0268/9217/3400/files/pokemon-tcg-perfect-order-booster-bundle.webp?v=1777386498",
      "lastSeen": "2026-07-18T15:09:59.508Z",
      "isPriceDrop": false,
      "oldPrice": null
    },
    {
      "id": "Double Sleeved::pokemon tcg: journey together - booster bundle",
      "product": "Pokemon TCG: Journey Together - Booster Bundle",
      "retailer": "Double Sleeved",
      "buyNow": 49.99,
      "rrp": 34.99,
      "resell": 45.04,
      "dealScore": 31,
      "grade": "H",
      "resellSource": "ebay_browse",
      "resellConfidence": "HIGH",
      "resellSampleSize": 10,
      "resellFreshness": "2026-07-18T15:10:00.077Z",
      "url": "https://www.doublesleeved.co.uk/products/pokemon-tcg-journey-together-booster-bundle",
      "image": "https://cdn.shopify.com/s/files/1/0268/9217/3400/files/pokemon-tcg-journey-together-booster-bundle.webp?v=1777304174",
      "lastSeen": "2026-07-18T15:10:00.328Z",
      "isPriceDrop": false,
      "oldPrice": null
    },
    {
      "id": "Double Sleeved::pokemon tcg: perfect order - booster pack",
      "product": "Pokemon TCG: Perfect Order - Booster Pack",
      "retailer": "Double Sleeved",
      "buyNow": 5.99,
      "rrp": 4.99,
      "resell": 7.48,
      "dealScore": 34,
      "grade": "H",
      "resellSource": "ebay_browse",
      "resellConfidence": "HIGH",
      "resellSampleSize": 9,
      "resellFreshness": "2026-07-18T15:10:00.923Z",
      "url": "https://www.doublesleeved.co.uk/products/pokemon-tcg-perfect-order-booster-pack",
      "image": "https://cdn.shopify.com/s/files/1/0268/9217/3400/files/Pokemon-TCG-Perfect-Order-Booster-Pack.webp?v=1776850280",
      "lastSeen": "2026-07-18T15:10:01.174Z",
      "isPriceDrop": false,
      "oldPrice": null
    },
    {
      "id": "Double Sleeved::pokemon tcg: perfect order - booster bundle case (25)",
      "product": "Pokemon TCG: Perfect Order - Booster Bundle Case (25)",
      "retailer": "Double Sleeved",
      "buyNow": 899,
      "rrp": 34.99,
      "resell": 69.48,
      "dealScore": 29,
      "grade": "H",
      "resellSource": "ebay_browse",
      "resellConfidence": "MEDIUM",
      "resellSampleSize": 5,
      "resellFreshness": "2026-07-18T15:10:01.794Z",
      "url": "https://www.doublesleeved.co.uk/products/pokemon-tcg-perfect-order-booster-bundle-case-25",
      "image": "https://cdn.shopify.com/s/files/1/0268/9217/3400/files/pokemon-tcg-perfect-order-booster-bundle-case.webp?v=1776352229",
      "lastSeen": "2026-07-18T15:10:02.045Z",
      "isPriceDrop": false,
      "oldPrice": null
    },
    {
      "id": "Double Sleeved::pokemon tcg: perfect order - booster box case",
      "product": "Pokemon TCG: Perfect Order - Booster Box Case",
      "retailer": "Double Sleeved",
      "buyNow": 1099,
      "rrp": 134.99,
      "resell": 115,
      "dealScore": 29,
      "grade": "H",
      "resellSource": "ebay_browse",
      "resellConfidence": "MEDIUM",
      "resellSampleSize": 4,
      "resellFreshness": "2026-07-18T15:10:02.671Z",
      "url": "https://www.doublesleeved.co.uk/products/pokemon-tcg-perfect-order-booster-box-case",
      "image": "https://cdn.shopify.com/s/files/1/0268/9217/3400/files/pokemon-tcg-perfect-order-booster-box-case.webp?v=1776351995",
      "lastSeen": "2026-07-18T15:10:02.922Z",
      "isPriceDrop": false,
      "oldPrice": null
    },
    {
      "id": "Double Sleeved::pokemon tcg: destined rivals - sleeved booster pack",
      "product": "Pokemon TCG: Destined Rivals - Sleeved Booster Pack",
      "retailer": "Double Sleeved",
      "buyNow": 9.99,
      "rrp": 4.99,
      "resell": 10.15,
      "dealScore": 28,
      "grade": "H",
      "resellSource": "ebay_browse",
      "resellConfidence": "MEDIUM",
      "resellSampleSize": 6,
      "resellFreshness": "2026-07-18T15:10:03.467Z",
      "url": "https://www.doublesleeved.co.uk/products/pokemon-tcg-destined-rivals-sleeved-booster-pack",
      "image": "https://cdn.shopify.com/s/files/1/0268/9217/3400/files/pokemon-tcg-destined-rivals-sleeved-booster-mewtwo.webp?v=1775658169",
      "lastSeen": "2026-07-18T15:10:03.717Z",
      "isPriceDrop": false,
      "oldPrice": null
    },
    {
      "id": "Double Sleeved::pokemon tcg: destined rivals - sleeved booster pack case (144)",
      "product": "Pokemon TCG: Destined Rivals - Sleeved Booster Pack Case (144)",
      "retailer": "Double Sleeved",
      "buyNow": 1399,
      "rrp": 4.99,
      "resell": 8,
      "dealScore": 30,
      "grade": "H",
      "resellSource": "static_table",
      "resellConfidence": null,
      "resellSampleSize": null,
      "resellFreshness": null,
      "url": "https://www.doublesleeved.co.uk/products/pokemon-tcg-destined-rivals-sleeved-booster-pack-case-144",
      "image": "https://cdn.shopify.com/s/files/1/0268/9217/3400/files/pokemon-tcg-destined-rivals-sleeved-booster-case-144.webp?v=1775575758",
      "lastSeen": "2026-07-18T15:10:04.482Z",
      "isPriceDrop": false,
      "oldPrice": null
    },
    {
      "id": "Double Sleeved::pokemon tcg: ascended heroes me2.5 - mini tins (set of 10)",
      "product": "Pokemon TCG: Ascended Heroes ME2.5 - Mini Tins (Set of 10)",
      "retailer": "Double Sleeved",
      "buyNow": 299.95,
      "rrp": 14.99,
      "resell": 29.4,
      "dealScore": 32,
      "grade": "H",
      "resellSource": "ebay_browse",
      "resellConfidence": "MEDIUM",
      "resellSampleSize": 6,
      "resellFreshness": "2026-07-18T15:10:05.126Z",
      "url": "https://www.doublesleeved.co.uk/products/pokemon-tcg-ascended-heroes-me2-5-mini-tins-set-of-10",
      "image": "https://cdn.shopify.com/s/files/1/0268/9217/3400/files/Pokemon-TCG-Ascended-Heroes-Mini-Tins-Set-Of-10.webp?v=1775142601",
      "lastSeen": "2026-07-18T15:10:05.377Z",
      "isPriceDrop": false,
      "oldPrice": null
    },
    {
      "id": "Double Sleeved::pokemon tcg: perfect order - booster box",
      "product": "Pokemon TCG: Perfect Order - Booster Box",
      "retailer": "Double Sleeved",
      "buyNow": 179.95,
      "rrp": 134.99,
      "resell": 142.58,
      "dealScore": 34,
      "grade": "H",
      "resellSource": "ebay_browse",
      "resellConfidence": "HIGH",
      "resellSampleSize": 13,
      "resellFreshness": "2026-07-18T15:10:05.954Z",
      "url": "https://www.doublesleeved.co.uk/products/pokemon-tcg-perfect-order-booster-box",
      "image": "https://cdn.shopify.com/s/files/1/0268/9217/3400/files/pokemon-tcg-perfect-order-booster-box.webp?v=1774532018",
      "lastSeen": "2026-07-18T15:10:06.205Z",
      "isPriceDrop": false,
      "oldPrice": null
    },
    {
      "id": "Double Sleeved::pokemon tcg: ascended heroes - booster pack",
      "product": "Pokemon TCG: Ascended Heroes - Booster Pack",
      "retailer": "Double Sleeved",
      "buyNow": 12.95,
      "rrp": 4.99,
      "resell": 13.37,
      "dealScore": 32,
      "grade": "H",
      "resellSource": "ebay_browse",
      "resellConfidence": "MEDIUM",
      "resellSampleSize": 5,
      "resellFreshness": "2026-07-18T15:10:07.048Z",
      "url": "https://www.doublesleeved.co.uk/products/pokemon-tcg-ascended-heores-booster-pack",
      "image": "https://cdn.shopify.com/s/files/1/0268/9217/3400/files/pokemon-tcg-ascended-heroes-booster-pack.webp?v=1774519401",
      "lastSeen": "2026-07-18T15:10:07.299Z",
      "isPriceDrop": false,
      "oldPrice": null
    }
  ],
  "holdData": {
    "151": {
      "score": 7,
      "trend": "rising",
      "yr1": 1.05,
      "yr2": 1.12,
      "yr3": 1.25,
      "yr4": 1.4,
      "note": "Charizard ex SIR (raw ~£80-100+), Mew ex SIR (raw ~£40-60+). Permanent nostalgia demand."
    },
    "evolving skies": {
      "score": 10,
      "trend": "rising",
      "yr1": 1.05,
      "yr2": 1.15,
      "yr3": 1.35,
      "yr4": 1.55,
      "note": "Umbreon VMAX Alt Art (raw ~£300-400+, PSA 10 ~£600+). Generational set — rarer every year."
    },
    "hidden fates": {
      "score": 9,
      "trend": "rising",
      "yr1": 1.05,
      "yr2": 1.12,
      "yr3": 1.25,
      "yr4": 1.4,
      "note": "Shiny Vault. All Shiny Pokemon — Shiny Charizard GX centrepiece."
    },
    "prismatic evolutions": {
      "score": 9,
      "trend": "rising",
      "yr1": 1.04,
      "yr2": 1.12,
      "yr3": 1.28,
      "yr4": 1.45,
      "note": "Umbreon ex SIR (raw ~£150-200+, PSA 10 ~£400+). Eevee demand permanent — next Evolving Skies."
    },
    "shining fates": {
      "score": 8,
      "trend": "rising",
      "yr1": 1.03,
      "yr2": 1.1,
      "yr3": 1.2,
      "yr4": 1.35,
      "note": "Shiny Charizard VMAX (raw ~£80-120+, PSA 10 ~£300+). Mini Shiny Vault. Print run ended."
    },
    "champions path": {
      "score": 9,
      "trend": "rising",
      "yr1": 1.06,
      "yr2": 1.15,
      "yr3": 1.3,
      "yr4": 1.5,
      "note": "Shiny Charizard V (raw ~£60-80+, PSA 10 ~£200+). Tiny print run, supply near exhausted."
    },
    "brilliant stars": {
      "score": 5,
      "trend": "stable",
      "yr1": 1.01,
      "yr2": 1.03,
      "yr3": 1.07,
      "yr4": 1.12,
      "note": "Charizard VSTAR (raw ~£40-80, PSA 10 ~£150+). Consistent collector and competitive demand."
    },
    "chilling reign": {
      "score": 7,
      "trend": "rising",
      "yr1": 1.04,
      "yr2": 1.1,
      "yr3": 1.2,
      "yr4": 1.35,
      "note": "Shadow Rider Calyrex VMAX (raw ~£40-60+), Ice Rider Alt Art (raw ~£60-80+). Undervalued."
    },
    "battle styles": {
      "score": 5,
      "trend": "stable",
      "yr1": 1.01,
      "yr2": 1.03,
      "yr3": 1.07,
      "yr4": 1.11,
      "note": "Urshifu V SWSH-Black Star (raw ~£8-20, PSA 10 ~£60+). Solid competitive and collector floor."
    },
    "fusion strike": {
      "score": 4,
      "trend": "stable",
      "yr1": 1.01,
      "yr2": 1.02,
      "yr3": 1.05,
      "yr4": 1.08,
      "note": "Gengar VMAX Alt Art (raw ~£60-80+, PSA 10 ~£150+). Large print run limits ceiling."
    },
    "astral radiance": {
      "score": 5,
      "trend": "stable",
      "yr1": 1.02,
      "yr2": 1.04,
      "yr3": 1.08,
      "yr4": 1.12,
      "note": "Origin Forme Palkia VSTAR (raw ~£25-50). Steady appreciation expected."
    },
    "lost origin": {
      "score": 6,
      "trend": "rising",
      "yr1": 1.03,
      "yr2": 1.08,
      "yr3": 1.15,
      "yr4": 1.25,
      "note": "Giratina VSTAR (raw ~£40-80, PSA 10 ~£120+). Increasingly popular collector target."
    },
    "silver tempest": {
      "score": 5,
      "trend": "stable",
      "yr1": 1.02,
      "yr2": 1.04,
      "yr3": 1.08,
      "yr4": 1.14,
      "note": "Regidrago VSTAR (raw ~£25-50). Modest but steady appreciation."
    },
    "crown zenith": {
      "score": 6,
      "trend": "rising",
      "yr1": 1.03,
      "yr2": 1.08,
      "yr3": 1.16,
      "yr4": 1.28,
      "note": "Galarian Gallery exclusives (raw ~£15-80 each). Strong collector appeal."
    },
    "surging sparks": {
      "score": 8,
      "trend": "rising",
      "yr1": 1.08,
      "yr2": 1.2,
      "yr3": 1.4,
      "yr4": 1.65,
      "note": "Pikachu ex SIR (raw ~£200-250+, PSA 10 ~£500+). Box prices up 150%+ in 18 months."
    },
    "destined rivals": {
      "score": 5,
      "trend": "stable",
      "yr1": 1.04,
      "yr2": 1.1,
      "yr3": 1.18,
      "yr4": 1.28,
      "note": "New set — chase cards TBC. Early buy window. Buy sealed and watch."
    },
    "temporal forces": {
      "score": 5,
      "trend": "stable",
      "yr1": 1.02,
      "yr2": 1.05,
      "yr3": 1.1,
      "yr4": 1.15,
      "note": "Walking Wake ex, Iron Leaves ex. Moderate collector interest."
    },
    "paradox rift": {
      "score": 5,
      "trend": "stable",
      "yr1": 1.02,
      "yr2": 1.05,
      "yr3": 1.1,
      "yr4": 1.15,
      "note": "Roaring Moon ex, Iron Valiant ex. Steady demand."
    },
    "paldean fates": {
      "score": 6,
      "trend": "rising",
      "yr1": 1.04,
      "yr2": 1.1,
      "yr3": 1.2,
      "yr4": 1.32,
      "note": "Shiny Vault mini-set. Shiny Charizard ex (raw ~£60-80+). Limited supply."
    },
    "obsidian flames": {
      "score": 5,
      "trend": "stable",
      "yr1": 1.02,
      "yr2": 1.05,
      "yr3": 1.09,
      "yr4": 1.14,
      "note": "Charizard ex SIR Tera (raw ~£50-100+). Popular Charizard variant."
    },
    "stellar crown": {
      "score": 4,
      "trend": "stable",
      "yr1": 1.01,
      "yr2": 1.03,
      "yr3": 1.06,
      "yr4": 1.1,
      "note": "Terapagos ex SIR (raw ~£30-40+). Modest appreciation expected."
    },
    "journey together": {
      "score": 4,
      "trend": "stable",
      "yr1": 1.02,
      "yr2": 1.05,
      "yr3": 1.08,
      "yr4": 1.12,
      "note": "New 2025 set. Chase cards developing — watch for key pulls."
    },
    "cosmic eclipse": {
      "score": 7,
      "trend": "rising",
      "yr1": 1.04,
      "yr2": 1.1,
      "yr3": 1.22,
      "yr4": 1.38,
      "note": "Arceus & Dialga TAG TEAM GX (raw ~£40-60+). Last Sun & Moon premium."
    },
    "vivid voltage": {
      "score": 5,
      "trend": "stable",
      "yr1": 1.01,
      "yr2": 1.03,
      "yr3": 1.06,
      "yr4": 1.1,
      "note": "Amazing Rares (raw ~£10-30 each). Moderate collector appeal."
    },
    "darkness ablaze": {
      "score": 4,
      "trend": "stable",
      "yr1": 1.01,
      "yr2": 1.02,
      "yr3": 1.05,
      "yr4": 1.08,
      "note": "Charizard VMAX (raw ~£30-50, PSA 10 ~£100+). Fan favourite consistent floor."
    },
    "rebel clash": {
      "score": 4,
      "trend": "stable",
      "yr1": 1.01,
      "yr2": 1.02,
      "yr3": 1.05,
      "yr4": 1.08,
      "note": "Inteleon VMAX (raw ~£10-20). Modest set with limited collector ceiling."
    },
    "ascended heroes": {
      "score": 8,
      "trend": "rising",
      "yr1": 1.08,
      "yr2": 1.18,
      "yr3": 1.35,
      "yr4": 1.55,
      "note": "Mega Evolution set. Mega Charizard ex (sealed UPC ~£150+). Growing demand."
    },
    "phantasmal flames": {
      "score": 7,
      "trend": "rising",
      "yr1": 1.06,
      "yr2": 1.14,
      "yr3": 1.28,
      "yr4": 1.45,
      "note": "Mega Evolution set. Mega Charizard variants drive collector demand."
    },
    "perfect order": {
      "score": 6,
      "trend": "rising",
      "yr1": 1.04,
      "yr2": 1.1,
      "yr3": 1.2,
      "yr4": 1.32,
      "note": "Mega Evolution set. Collector demand growing as series matures."
    }
  },
  "updatedAt": "2026-07-18T15:10:07.299Z"
}