{
  "deals": [
    {
      "id": "v1|147312818006|0",
      "title": "Pokemon TCG Champions Path Elite Trainer Box ETB ** New & Sealed ** READ DESC!!",
      "type": "ETB",
      "price": 119.99,
      "marketFloor": 200,
      "marketCeil": 380,
      "midMarket": 290,
      "netProfit": 128.3,
      "roi": 107,
      "pctBelow": 40,
      "image": "https://i.ebayimg.com/images/g/u8YAAeSwo1lqB6po/s-l1600.jpg",
      "url": "https://www.ebay.co.uk/itm/147312818006?_skw=pokemon+champions+path+elite+trainer+box+sealed&hash=item224c873756:g:u8YAAeSwo1lqB6po",
      "condition": "New/Factory Sealed",
      "source": "ebay_live",
      "scannedAt": "2026-05-17T13:19:16.897Z"
    },
    {
      "id": "v1|227347287691|0",
      "title": "Pokemon TCG Champions Path ETB Elite Trainer Box - Sealed ",
      "type": "ETB",
      "price": 123,
      "marketFloor": 200,
      "marketCeil": 380,
      "midMarket": 290,
      "netProfit": 125.29,
      "roi": 102,
      "pctBelow": 39,
      "image": "https://i.ebayimg.com/images/g/uZ4AAeSwX9xqCaSp/s-l1600.jpg",
      "url": "https://www.ebay.co.uk/itm/227347287691?_skw=pokemon+champions+path+elite+trainer+box+sealed&hash=item34eef44e8b:g:uZ4AAeSwX9xqCaSp",
      "condition": "New/Factory Sealed",
      "source": "ebay_live",
      "scannedAt": "2026-05-17T13:19:16.897Z"
    },
    {
      "id": "v1|358398826663|0",
      "title": "🔥Kyurem V Box Pokémon 🔥2 x Evolving Skies & 2 x Lost Origin🔥Sealed Collection",
      "type": "Booster Box",
      "price": 95.34,
      "marketFloor": 190,
      "marketCeil": 260,
      "midMarket": 225,
      "netProfit": 96.33,
      "roi": 101,
      "pctBelow": 50,
      "image": "https://i.ebayimg.com/images/g/UkYAAeSwwetpzVDx/s-l1600.jpg",
      "url": "https://www.ebay.co.uk/itm/358398826663?_skw=pokemon+evolving+skies+booster+box+sealed&hash=item53723c18a7:g:UkYAAeSwwetpzVDx",
      "condition": "New/Factory Sealed",
      "source": "ebay_live",
      "scannedAt": "2026-05-17T13:19:04.417Z"
    },
    {
      "id": "v1|397855883466|0",
      "title": "Pokemon Champion's Path Elite Trainer Box SEALED",
      "type": "ETB",
      "price": 125,
      "marketFloor": 200,
      "marketCeil": 380,
      "midMarket": 290,
      "netProfit": 123.29,
      "roi": 99,
      "pctBelow": 38,
      "image": "https://i.ebayimg.com/images/g/guIAAeSwKOdp5CqR/s-l1600.jpg",
      "url": "https://www.ebay.co.uk/itm/397855883466?_skw=pokemon+champions+path+elite+trainer+box+sealed&hash=item5ca20f00ca:g:guIAAeSwKOdp5CqR",
      "condition": "New/Factory Sealed",
      "source": "ebay_live",
      "scannedAt": "2026-05-17T13:19:16.897Z"
    },
    {
      "id": "v1|157915471412|0",
      "title": "Pokemon TCG Champions Path ETB Elite Trainer Box New Sealed",
      "type": "ETB",
      "price": 125.5,
      "marketFloor": 200,
      "marketCeil": 380,
      "midMarket": 290,
      "netProfit": 122.79,
      "roi": 98,
      "pctBelow": 37,
      "image": "https://i.ebayimg.com/images/g/wt0AAeSw5D5p3QPv/s-l1600.jpg",
      "url": "https://www.ebay.co.uk/itm/157915471412?_skw=pokemon+champions+path+elite+trainer+box+sealed&hash=item24c47ede34:g:wt0AAeSw5D5p3QPv",
      "condition": "New/Factory Sealed",
      "source": "ebay_live",
      "scannedAt": "2026-05-17T13:19:16.897Z"
    },
    {
      "id": "v1|127808130031|0",
      "title": "Pokemon TCG Champions Path Elite Trainer Box ETB ** New & Sealed **",
      "type": "ETB",
      "price": 130.7,
      "marketFloor": 200,
      "marketCeil": 380,
      "midMarket": 290,
      "netProfit": 117.59,
      "roi": 90,
      "pctBelow": 35,
      "image": "https://i.ebayimg.com/images/g/eAwAAeSw5ZZp3QN1/s-l1600.jpg",
      "url": "https://www.ebay.co.uk/itm/127808130031?_skw=pokemon+champions+path+elite+trainer+box+sealed&hash=item1dc1f54bef:g:eAwAAeSw5ZZp3QN1",
      "condition": "New/Factory Sealed",
      "source": "ebay_live",
      "scannedAt": "2026-05-17T13:19:16.897Z"
    },
    {
      "id": "v1|227307628491|0",
      "title": "Champions Path Pokemon Sealed Elite Trainer Box ",
      "type": "ETB",
      "price": 130.7,
      "marketFloor": 200,
      "marketCeil": 380,
      "midMarket": 290,
      "netProfit": 117.59,
      "roi": 90,
      "pctBelow": 35,
      "image": "https://i.ebayimg.com/images/g/saUAAeSw9zpp5Ln4/s-l1600.jpg",
      "url": "https://www.ebay.co.uk/itm/227307628491?_skw=pokemon+champions+path+elite+trainer+box+sealed&hash=item34ec9727cb:g:saUAAeSw9zpp5Ln4",
      "condition": "New/Factory Sealed",
      "source": "ebay_live",
      "scannedAt": "2026-05-17T13:19:16.897Z"
    },
    {
      "id": "v1|188305042127|0",
      "title": "Pokemon TCG: Sword & Shield  Chilling Reign Sealed - Elite Trainer Box",
      "type": "Booster Box",
      "price": 114.99,
      "marketFloor": 220,
      "marketCeil": 290,
      "midMarket": 255,
      "netProfit": 102.81,
      "roi": 89,
      "pctBelow": 48,
      "image": "https://i.ebayimg.com/images/g/GLcAAeSwI3Zp6OKQ/s-l1600.jpg",
      "url": "https://www.ebay.co.uk/itm/188305042127?_skw=pokemon+chilling+reign+booster+box+sealed&hash=item2bd7daeacf:g:GLcAAeSwI3Zp6OKQ",
      "condition": "New/Factory Sealed",
      "source": "ebay_live",
      "scannedAt": "2026-05-17T13:19:09.656Z"
    },
    {
      "id": "v1|188305044906|0",
      "title": "Pokemon TCG: Sword & Shield  Chilling Reign Sealed - Elite Trainer Box",
      "type": "Booster Box",
      "price": 114.99,
      "marketFloor": 220,
      "marketCeil": 290,
      "midMarket": 255,
      "netProfit": 102.81,
      "roi": 89,
      "pctBelow": 48,
      "image": "https://i.ebayimg.com/images/g/W5EAAeSwLUpp6ONi/s-l1600.jpg",
      "url": "https://www.ebay.co.uk/itm/188305044906?_skw=pokemon+chilling+reign+booster+box+sealed&hash=item2bd7daf5aa:g:W5EAAeSwLUpp6ONi",
      "condition": "New/Factory Sealed",
      "source": "ebay_live",
      "scannedAt": "2026-05-17T13:19:09.656Z"
    },
    {
      "id": "v1|188383223688|0",
      "title": "Pokémon Sword and Shield Battle Styles Elite Trainer Box ETB Red New Sealed",
      "type": "Booster Box",
      "price": 130.7,
      "marketFloor": 250,
      "marketCeil": 320,
      "midMarket": 285,
      "netProfit": 113.24,
      "roi": 87,
      "pctBelow": 48,
      "image": "https://i.ebayimg.com/images/g/j4IAAeSwzrlqBhyp/s-l1600.jpg",
      "url": "https://www.ebay.co.uk/itm/188383223688?_skw=pokemon+battle+styles+booster+box+sealed&hash=item2bdc83df88:g:j4IAAeSwzrlqBhyp",
      "condition": "New/Factory Sealed",
      "source": "ebay_live",
      "scannedAt": "2026-05-17T13:19:20.649Z"
    },
    {
      "id": "v1|287290374441|0",
      "title": "Pokemon Card Sleeves - Pokemon 151 - Elite Trainer Box Sleeves - Sealed Pack x65",
      "type": "ETB",
      "price": 31.9,
      "marketFloor": 55,
      "marketCeil": 90,
      "midMarket": 72.5,
      "netProfit": 26.95,
      "roi": 84,
      "pctBelow": 42,
      "image": "https://i.ebayimg.com/images/g/sasAAeSw69Jp6qH1/s-l1600.jpg",
      "url": "https://www.ebay.co.uk/itm/287290374441?_skw=pokemon+151+elite+trainer+box+sealed&hash=item42e3d73929:g:sasAAeSw69Jp6qH1",
      "condition": "New",
      "source": "ebay_live",
      "scannedAt": "2026-05-17T13:19:15.114Z"
    },
    {
      "id": "v1|389941730398|0",
      "title": "Pokémon Champion's Path Elite Trainer Box New & Sealed",
      "type": "ETB",
      "price": 135,
      "marketFloor": 200,
      "marketCeil": 380,
      "midMarket": 290,
      "netProfit": 113.29,
      "roi": 84,
      "pctBelow": 32,
      "image": "https://i.ebayimg.com/images/g/oTsAAeSwI8dp7kda/s-l1600.jpg",
      "url": "https://www.ebay.co.uk/itm/389941730398?_skw=pokemon+champions+path+elite+trainer+box+sealed&hash=item5aca569c5e:g:oTsAAeSwI8dp7kda",
      "condition": "New/Factory Sealed",
      "source": "ebay_live",
      "scannedAt": "2026-05-17T13:19:16.897Z"
    },
    {
      "id": "v1|327112095150|0",
      "title": "Pokemon TCG Champions Path Elite Trainer Box  New & Sealed",
      "type": "ETB",
      "price": 135.9,
      "marketFloor": 200,
      "marketCeil": 380,
      "midMarket": 290,
      "netProfit": 112.39,
      "roi": 83,
      "pctBelow": 32,
      "image": "https://i.ebayimg.com/images/g/jkwAAeSwQ5do-fQG/s-l1200.jpg",
      "url": "https://www.ebay.co.uk/itm/327112095150?_skw=pokemon+champions+path+elite+trainer+box+sealed&hash=item4c296675ae:g:jkwAAeSwQ5do-fQG",
      "condition": "New/Factory Sealed",
      "source": "ebay_live",
      "scannedAt": "2026-05-17T13:19:16.897Z"
    },
    {
      "id": "v1|389360208837|0",
      "title": "Pokemon Champion's Path Elite Trainer Box",
      "type": "ETB",
      "price": 135.9,
      "marketFloor": 200,
      "marketCeil": 380,
      "midMarket": 290,
      "netProfit": 112.39,
      "roi": 83,
      "pctBelow": 32,
      "image": "https://i.ebayimg.com/images/g/6W0AAeSwcxppOst4/s-l1600.jpg",
      "url": "https://www.ebay.co.uk/itm/389360208837?_skw=pokemon+champions+path+elite+trainer+box+sealed&hash=item5aa7ad4bc5:g:6W0AAeSwcxppOst4",
      "condition": "New/Factory Sealed",
      "source": "ebay_live",
      "scannedAt": "2026-05-17T13:19:16.897Z"
    },
    {
      "id": "v1|257468860110|0",
      "title": "BRAND NEW & SEALED Pokemon TCG Champion’s Path Elite Trainer Box",
      "type": "ETB",
      "price": 135.9,
      "marketFloor": 200,
      "marketCeil": 380,
      "midMarket": 290,
      "netProfit": 112.39,
      "roi": 83,
      "pctBelow": 32,
      "image": "https://i.ebayimg.com/images/g/i1kAAeSw6qZoqJMr/s-l1600.jpg",
      "url": "https://www.ebay.co.uk/itm/257468860110?_skw=pokemon+champions+path+elite+trainer+box+sealed&hash=item3bf25706ce:g:i1kAAeSw6qZoqJMr",
      "condition": "New/Factory Sealed",
      "source": "ebay_live",
      "scannedAt": "2026-05-17T13:19:16.897Z"
    },
    {
      "id": "v1|287319729554|0",
      "title": "Pokemon - Chilling Reign Elite Trainer Box - Sword & Shield - NEW FACTORY SEALED",
      "type": "Booster Box",
      "price": 120.5,
      "marketFloor": 220,
      "marketCeil": 290,
      "midMarket": 255,
      "netProfit": 97.31,
      "roi": 81,
      "pctBelow": 45,
      "image": "https://i.ebayimg.com/images/g/XocAAeSwvSpp~elO/s-l1600.jpg",
      "url": "https://www.ebay.co.uk/itm/287319729554?_skw=pokemon+chilling+reign+booster+box+sealed&hash=item42e5972592:g:XocAAeSwvSpp~elO",
      "condition": "New/Factory Sealed",
      "source": "ebay_live",
      "scannedAt": "2026-05-17T13:19:09.656Z"
    },
    {
      "id": "v1|168301564678|0",
      "title": "Pokemon TCG Champions Path Elite Trainer Box ETB New & Sealed",
      "type": "ETB",
      "price": 139,
      "marketFloor": 200,
      "marketCeil": 380,
      "midMarket": 290,
      "netProfit": 109.29,
      "roi": 79,
      "pctBelow": 31,
      "image": "https://i.ebayimg.com/images/g/0RMAAeSwETJp2Ve3/s-l1600.jpg",
      "url": "https://www.ebay.co.uk/itm/168301564678?_skw=pokemon+champions+path+elite+trainer+box+sealed&hash=item272f8e1306:g:0RMAAeSwETJp2Ve3",
      "condition": "New/Factory Sealed",
      "source": "ebay_live",
      "scannedAt": "2026-05-17T13:19:16.897Z"
    },
    {
      "id": "v1|357790987747|0",
      "title": "Eevee SVP 173 Prismatic Evolutions Elite Trainer Box Promo Pokémon TCG SEALED",
      "type": "ETB",
      "price": 40.01,
      "marketFloor": 60,
      "marketCeil": 110,
      "midMarket": 85,
      "netProfit": 29.73,
      "roi": 74,
      "pctBelow": 33,
      "image": "https://i.ebayimg.com/images/g/sVwAAeSw6Zho-AtH/s-l1600.jpg",
      "url": "https://www.ebay.co.uk/itm/357790987747?_skw=pokemon+prismatic+evolutions+elite+trainer+box+sealed&hash=item534e0135e3:g:sVwAAeSw6Zho-AtH",
      "condition": "Ungraded",
      "source": "ebay_live",
      "scannedAt": "2026-05-17T13:19:07.922Z"
    },
    {
      "id": "v1|287321645619|0",
      "title": "Chilling Reign Elite Trainer Box New & Sealed Sword and Shield Pokemon TCG",
      "type": "Booster Box",
      "price": 125,
      "marketFloor": 220,
      "marketCeil": 290,
      "midMarket": 255,
      "netProfit": 92.81,
      "roi": 74,
      "pctBelow": 43,
      "image": "https://i.ebayimg.com/images/g/L20AAeSwi69p~yj5/s-l1600.jpg",
      "url": "https://www.ebay.co.uk/itm/287321645619?_skw=pokemon+chilling+reign+booster+box+sealed&hash=item42e5b46233:g:L20AAeSwi69p~yj5",
      "condition": "New/Factory Sealed",
      "source": "ebay_live",
      "scannedAt": "2026-05-17T13:19:09.656Z"
    },
    {
      "id": "v1|147306118112|0",
      "title": "Pokemon TCG Champions Path Elite Trainer Box (ETB)  -  Brand New & Sealed",
      "type": "ETB",
      "price": 145.02,
      "marketFloor": 200,
      "marketCeil": 380,
      "midMarket": 290,
      "netProfit": 103.27,
      "roi": 71,
      "pctBelow": 27,
      "image": "https://i.ebayimg.com/images/g/twYAAeSwz2NpWR-w/s-l1600.jpg",
      "url": "https://www.ebay.co.uk/itm/147306118112?_skw=pokemon+champions+path+elite+trainer+box+sealed&hash=item224c20fbe0:g:twYAAeSwz2NpWR-w",
      "condition": "New/Factory Sealed",
      "source": "ebay_live",
      "scannedAt": "2026-05-17T13:19:16.897Z"
    },
    {
      "id": "v1|287303471114|0",
      "title": "Pokemon Champions Path Elite Trainer Box New Factory Sealed",
      "type": "ETB",
      "price": 146.3,
      "marketFloor": 200,
      "marketCeil": 380,
      "midMarket": 290,
      "netProfit": 101.99,
      "roi": 70,
      "pctBelow": 27,
      "image": "https://i.ebayimg.com/images/g/HVQAAeSwZqJp836v/s-l1200.jpg",
      "url": "https://www.ebay.co.uk/itm/287303471114?_skw=pokemon+champions+path+elite+trainer+box+sealed&hash=item42e49f100a:g:HVQAAeSwZqJp836v",
      "condition": "New/Factory Sealed",
      "source": "ebay_live",
      "scannedAt": "2026-05-17T13:19:16.897Z"
    },
    {
      "id": "v1|406489732726|0",
      "title": "Champion's Path Elite Trainer Box + Case Sealed ETB - Pokemon TCG Champions Path",
      "type": "ETB",
      "price": 146,
      "marketFloor": 200,
      "marketCeil": 380,
      "midMarket": 290,
      "netProfit": 102.29,
      "roi": 70,
      "pctBelow": 27,
      "image": "https://i.ebayimg.com/images/g/QgIAAeSwdLRpQpuJ/s-l1600.jpg",
      "url": "https://www.ebay.co.uk/itm/406489732726?_skw=pokemon+champions+path+elite+trainer+box+sealed&hash=item5ea4ad1676:g:QgIAAeSwdLRpQpuJ",
      "condition": "New/Factory Sealed",
      "source": "ebay_live",
      "scannedAt": "2026-05-17T13:19:16.897Z"
    },
    {
      "id": "v1|205734731822|0",
      "title": "Pokemon TCG Champion's Path: CHARIZARD ELITE TRAINER BOX ETB New Sealed in Hand",
      "type": "ETB",
      "price": 146.3,
      "marketFloor": 200,
      "marketCeil": 380,
      "midMarket": 290,
      "netProfit": 101.99,
      "roi": 70,
      "pctBelow": 27,
      "image": "https://i.ebayimg.com/images/g/z6wAAeSwbgxozTYp/s-l1600.jpg",
      "url": "https://www.ebay.co.uk/itm/205734731822?_skw=pokemon+champions+path+elite+trainer+box+sealed&hash=item2fe6bee02e:g:z6wAAeSwbgxozTYp",
      "condition": "New/Factory Sealed",
      "source": "ebay_live",
      "scannedAt": "2026-05-17T13:19:16.897Z"
    },
    {
      "id": "v1|127629668419|0",
      "title": "SEALED! Snorlax SVP 051 151 Elite Trainer Box ETB Promo Pokemon Card! FREE P&P!",
      "type": "ETB",
      "price": 34.99,
      "marketFloor": 55,
      "marketCeil": 90,
      "midMarket": 72.5,
      "netProfit": 23.86,
      "roi": 68,
      "pctBelow": 36,
      "image": "https://i.ebayimg.com/images/g/lsIAAeSwY0ppwUdg/s-l1600.jpg",
      "url": "https://www.ebay.co.uk/itm/127629668419?_skw=pokemon+151+elite+trainer+box+sealed&hash=item1db7523043:g:lsIAAeSwY0ppwUdg",
      "condition": "Ungraded",
      "source": "ebay_live",
      "scannedAt": "2026-05-17T13:19:15.114Z"
    },
    {
      "id": "v1|277952115686|0",
      "title": "Pokemon Champions Path Elite Trainer Box ETB New & Sealed",
      "type": "ETB",
      "price": 148.85,
      "marketFloor": 200,
      "marketCeil": 380,
      "midMarket": 290,
      "netProfit": 99.44,
      "roi": 67,
      "pctBelow": 26,
      "image": "https://i.ebayimg.com/images/g/bn4AAeSwl5xp9vDL/s-l1600.jpg",
      "url": "https://www.ebay.co.uk/itm/277952115686?_skw=pokemon+champions+path+elite+trainer+box+sealed&hash=item40b73cb3e6:g:bn4AAeSwl5xp9vDL",
      "condition": "New/Factory Sealed",
      "source": "ebay_live",
      "scannedAt": "2026-05-17T13:19:16.897Z"
    },
    {
      "id": "v1|306933062719|0",
      "title": "*New & Sealed* Pokemon TCG Champions Path Elite Trainer Box ETB",
      "type": "ETB",
      "price": 149.99,
      "marketFloor": 200,
      "marketCeil": 380,
      "midMarket": 290,
      "netProfit": 98.3,
      "roi": 66,
      "pctBelow": 25,
      "image": "https://i.ebayimg.com/images/g/CUkAAeSwA7pqAl06/s-l1600.jpg",
      "url": "https://www.ebay.co.uk/itm/306933062719?_skw=pokemon+champions+path+elite+trainer+box+sealed&hash=item4776a2dc3f:g:CUkAAeSwA7pqAl06",
      "condition": "New/Factory Sealed",
      "source": "ebay_live",
      "scannedAt": "2026-05-17T13:19:16.897Z"
    },
    {
      "id": "v1|198357423363|0",
      "title": "Chilling Reign Elite Trainer Box - Pokémon TCG New Sealed",
      "type": "Booster Box",
      "price": 146.3,
      "marketFloor": 220,
      "marketCeil": 290,
      "midMarket": 255,
      "netProfit": 71.5,
      "roi": 49,
      "pctBelow": 34,
      "image": "https://i.ebayimg.com/images/g/46QAAeSw--9p~f94/s-l1600.jpg",
      "url": "https://www.ebay.co.uk/itm/198357423363?_skw=pokemon+chilling+reign+booster+box+sealed&hash=item2e2f061503:g:46QAAeSw--9p~f94",
      "condition": "New/Factory Sealed",
      "source": "ebay_live",
      "scannedAt": "2026-05-17T13:19:09.656Z"
    },
    {
      "id": "v1|366311472679|0",
      "title": "Pokemon TCG Chinese Stars Collection Hidden Fates Booster Box Factory Sealed",
      "type": "Booster Box",
      "price": 149.99,
      "marketFloor": 200,
      "marketCeil": 320,
      "midMarket": 260,
      "netProfit": 72.17,
      "roi": 48,
      "pctBelow": 25,
      "image": "https://i.ebayimg.com/images/g/kKcAAeSwu9xo5bgz/s-l1600.jpg",
      "url": "https://www.ebay.co.uk/itm/366311472679?_skw=pokemon+hidden+fates+booster+box+sealed&hash=item5549dd7e27:g:kKcAAeSwu9xo5bgz",
      "condition": "New/Factory Sealed",
      "source": "ebay_live",
      "scannedAt": "2026-05-17T13:19:06.170Z"
    },
    {
      "id": "v1|168262064970|0",
      "title": "Pokemon TCG Chilling Reign Elite Trainer Box with Tin Costco Bundle, New Sealed",
      "type": "Booster Box",
      "price": 177.5,
      "marketFloor": 220,
      "marketCeil": 290,
      "midMarket": 255,
      "netProfit": 40.3,
      "roi": 23,
      "pctBelow": 19,
      "image": "https://i.ebayimg.com/images/g/O-EAAeSw~ZdpxBj6/s-l1600.jpg",
      "url": "https://www.ebay.co.uk/itm/168262064970?_skw=pokemon+chilling+reign+booster+box+sealed&hash=item272d335b4a:g:O-EAAeSw~ZdpxBj6",
      "condition": "New/Factory Sealed",
      "source": "ebay_live",
      "scannedAt": "2026-05-17T13:19:09.656Z"
    },
    {
      "id": "v1|306939083120|0",
      "title": "Pokemon TCG Chilling Reign Elite Trainer Box Tin Costco Bundle New Sealed FAST🚚",
      "type": "Booster Box",
      "price": 189.98,
      "marketFloor": 220,
      "marketCeil": 290,
      "midMarket": 255,
      "netProfit": 27.83,
      "roi": 15,
      "pctBelow": 14,
      "image": "https://i.ebayimg.com/images/g/TakAAeSwa5xqBh5-/s-l1600.jpg",
      "url": "https://www.ebay.co.uk/itm/306939083120?_skw=pokemon+chilling+reign+booster+box+sealed&hash=item4776feb970:g:TakAAeSwa5xqBh5-",
      "condition": "New/Factory Sealed",
      "source": "ebay_live",
      "scannedAt": "2026-05-17T13:19:09.656Z"
    },
    {
      "id": "v1|147312714420|0",
      "title": "Pokemon Sword & Shield Battle Styles Factory Sealed Booster Box 36 Packs",
      "type": "Booster Box",
      "price": 220,
      "marketFloor": 250,
      "marketCeil": 320,
      "midMarket": 285,
      "netProfit": 23.94,
      "roi": 11,
      "pctBelow": 12,
      "image": "https://i.ebayimg.com/images/g/KKYAAeSwd2xqB5Oc/s-l1600.jpg",
      "url": "https://www.ebay.co.uk/itm/147312714420?_skw=pokemon+battle+styles+booster+box+sealed&hash=item224c85a2b4:g:KKYAAeSwd2xqB5Oc",
      "condition": "New/Factory Sealed",
      "source": "ebay_live",
      "scannedAt": "2026-05-17T13:19:20.649Z"
    },
    {
      "id": "v1|127697464371|0",
      "title": "Pokemon Chilling Reign Elite Trainer Box 2-Pack - Brand New & Sealed",
      "type": "Booster Box",
      "price": 200,
      "marketFloor": 220,
      "marketCeil": 290,
      "midMarket": 255,
      "netProfit": 17.8,
      "roi": 9,
      "pctBelow": 9,
      "image": "https://i.ebayimg.com/images/g/sgwAAeSw1mxpmee-/s-l1600.jpg",
      "url": "https://www.ebay.co.uk/itm/127697464371?_skw=pokemon+chilling+reign+booster+box+sealed&hash=item1dbb5cac33:g:sgwAAeSw1mxpmee-",
      "condition": "New/Factory Sealed",
      "source": "ebay_live",
      "scannedAt": "2026-05-17T13:19:09.656Z"
    }
  ],
  "updatedAt": "2026-05-17T13:19:22.125Z",
  "count": 32
}